bluerpc/__init__.py
bluerpc/ble_conn.py
bluerpc/ble_scan.py
bluerpc/cli.py
bluerpc/discovery.py
bluerpc/log.py
bluerpc/service.py
bluerpc/utils.py
bluerpc/rpc/__init__.py
bluerpc/rpc/common_pb2.py
bluerpc/rpc/common_pb2_grpc.py
bluerpc/rpc/gatt_pb2.py
bluerpc/rpc/gatt_pb2_grpc.py
bluerpc/rpc/services_pb2.py
bluerpc/rpc/services_pb2_grpc.py
bluerpc-0.3.4.dist-info/METADATA
bluerpc-0.3.4.dist-info/WHEEL
bluerpc-0.3.4.dist-info/entry_points.txt
bluerpc-0.3.4.dist-info/top_level.txt
bluerpc-0.3.4.dist-info/RECORD
