Metadata-Version: 2.1
Name: bluerpc
Version: 0.3.4
Summary: Python BlueRPC Worker
Home-page: https://github.com/BlueRPC/BlueRPC
Author: drosocode
License: MIT
Project-URL: Documentation, https://bluerpc.github.io/
Project-URL: Source, https://github.com/BlueRPC/BlueRPC/tree/main/python
Classifier: Programming Language :: Python :: 3
Classifier: License :: OSI Approved :: MIT License
Classifier: Operating System :: OS Independent
Requires-Python: >=3.10
Requires-Dist: bleak
Requires-Dist: bluetooth-adapters
Requires-Dist: cryptography
Requires-Dist: grpcio
Requires-Dist: grpc-interceptor
Requires-Dist: protobuf
Requires-Dist: netifaces
Requires-Dist: zeroconf
